{
  "HVIGOR_OHOS_PLUGIN": {
    "MODULES": [
      {
        "MODULE_NAME": "1043bfc77febe75fafec0c4309faccf1",
        "API_TYPE": "stageMode",
        "INCREMENTAL_TASKS": {
          "COMPILE_ARKTS": true
        }
      }
    ],
    "NATIVE_COMPILER": "Default",
    "BUILD_MODE": "debug"
  },
  "HVIGOR": {
    "IS_INCREMENTAL": true,
    "IS_DAEMON": true,
    "IS_PARALLEL": true,
    "IS_HVIGORFILE_TYPE_CHECK": false,
    "TASK_TIME": {
      "1043bfc77febe75fafec0c4309faccf1": {
        "CreateModuleInfo": 2926300,
        "ConfigureCmake": 1580300,
        "PreCheckSyscap": 2116100,
        "GeneratePkgContextInfo": 19913000,
        "ProcessIntegratedHsp": 3665800,
        "BuildNativeWithCmake": 1470000,
        "SyscapTransform": 22272700,
        "ProcessStartupConfig": 7236800,
        "BuildNativeWithNinja": 3526200,
        "BuildJS": 9475000,
        "CompileArkTS": 3977286300,
        "ProcessCompiledResources": 2878700,
        "PackageHap": 145226400,
        "PackingCheck": 18772200,
        "SignHap": 7776500,
        "CollectDebugSymbol": 8833100,
        "assembleHap": 2002400
      }
    },
    "APIS": [
      "getHvigorConfig",
      "getRootNodeDescriptor",
      "getChildNode",
      "getNodeByName",
      "getAllNodes",
      "getRootNode",
      "getNodeName",
      "getNodePath",
      "subNodes",
      "getExtraOption",
      "getExtParam",
      "getExtParams",
      "getProperty",
      "getProperties",
      "getProductName",
      "nodesEvaluated",
      "getParameter",
      "getCommandEntryTask",
      "getStartParams"
    ],
    "CONFIG_PROPERTIES": {},
    "TOTAL_TIME": 5147603900,
    "BUILD_ID": "202511211735411770"
  }
}